aionotion/__init__.py
aionotion/bridge/__init__.py
aionotion/bridge/models.py
aionotion/client.py
aionotion/const.py
aionotion/errors.py
aionotion/listener/__init__.py
aionotion/listener/models.py
aionotion/py.typed
aionotion/sensor/__init__.py
aionotion/sensor/models.py
aionotion/system/__init__.py
aionotion/system/models.py
aionotion/user/__init__.py
aionotion/user/models.py
aionotion/util/__init__.py
aionotion/util/auth.py
aionotion/util/dt.py
aionotion-2024.3.1.dist-info/LICENSE
aionotion-2024.3.1.dist-info/METADATA
aionotion-2024.3.1.dist-info/WHEEL
aionotion-2024.3.1.dist-info/RECORD
